aif_custom_tools/AIF_client.py
aif_custom_tools/__init__.py
aif_custom_tools/tools/AIF_client.py
aif_custom_tools/tools/__init__.py
aif_custom_tools/tools/custom_llm_tool.py
aif_custom_tools/tools/utils.py
aif_custom_tools/yamls/custom_llm_tool.yaml
tests/__init__.py
tests/test_custom_llm_tool.py
aif_custom_tools-0.0.4.dist-info/METADATA
aif_custom_tools-0.0.4.dist-info/WHEEL
aif_custom_tools-0.0.4.dist-info/entry_points.txt
aif_custom_tools-0.0.4.dist-info/top_level.txt
aif_custom_tools-0.0.4.dist-info/RECORD
