Metadata-Version: 2.1
Name: aif-custom-tools
Version: 0.0.4
Summary: This is my tools package
